<?xml version="1.0" encoding="utf-8"?>
<LanguageData>

  <DrankUrine.stages.0.label>오줌을 마심</DrankUrine.stages.0.label>
  <DrankUrine.stages.0.description>내 자신의 소변을 마셔야하다니...</DrankUrine.stages.0.description>

  <WashPrivacy.stages.0.label>부끄러움</WashPrivacy.stages.0.label>
  <WashPrivacy.stages.0.description>실수로 남이 목욕하는걸 봤어...</WashPrivacy.stages.0.description>

  <ToiletPrivacy.stages.0.label>부끄러움</ToiletPrivacy.stages.0.label>
  <ToiletPrivacy.stages.0.description>내가 화장실을 사용하는걸 남이 봤어!</ToiletPrivacy.stages.0.description>

  <SoiledSelf.stages.0.label>더러움</SoiledSelf.stages.0.label>
  <SoiledSelf.stages.0.description>씼고싶다아아악</SoiledSelf.stages.0.description>

  <HotShower.stages.0.label>따뜻한 샤워</HotShower.stages.0.label>
  <HotShower.stages.0.description>따듯한 물로 샤워했어</HotShower.stages.0.description>

  <HotBath.stages.0.label>따뜻한 목욕</HotBath.stages.0.label>
  <HotBath.stages.0.description>따뜻한 물로 목욕했어</HotBath.stages.0.description>

  <ColdBath.stages.0.label>차가운 목욕</ColdBath.stages.0.label>
  <ColdBath.stages.0.description>시원하게 목욕했어!</ColdBath.stages.0.description>

  <ColdShower.stages.0.label>Cold Shower</ColdShower.stages.0.label>
  <ColdShower.stages.0.description>시원하게 샤워했어!</ColdShower.stages.0.description>

  <ColdWater.stages.0.label>차가운물</ColdWater.stages.0.label>
  <ColdWater.stages.0.description>뜨거운 물이 안나와!</ColdWater.stages.0.description>

  <tookDump.stages.0.label>마음이 진정됨</tookDump.stages.0.label>
  <tookDump.stages.0.description>훨씬 좋군.</tookDump.stages.0.description>

  <openDefecation.stages.0.label>밖에서 쌈</openDefecation.stages.0.label>
  <openDefecation.stages.0.description>화장실을 못찾아서 밖에서 싸야했어</openDefecation.stages.0.description>

  <UsedPrivateBathroom.stages.0.label>끔찍한욕실</UsedPrivateBathroom.stages.0.label>
  <UsedPrivateBathroom.stages.0.description>내 욕실은 끔찍해</UsedPrivateBathroom.stages.0.description>
  <UsedPrivateBathroom.stages.3.label>괜찮은 욕실</UsedPrivateBathroom.stages.3.label>
  <UsedPrivateBathroom.stages.3.description>맘에드는 욕실이야.</UsedPrivateBathroom.stages.3.description>
  <UsedPrivateBathroom.stages.4.label>약간 인상적인 욕실</UsedPrivateBathroom.stages.4.label>
  <UsedPrivateBathroom.stages.4.description>내 욕실은 약간 인상적이야.</UsedPrivateBathroom.stages.4.description>
  <UsedPrivateBathroom.stages.5.label>인상적인 욕실</UsedPrivateBathroom.stages.5.label>
  <UsedPrivateBathroom.stages.5.description>내 욕실은 인상적이야</UsedPrivateBathroom.stages.5.description>
  <UsedPrivateBathroom.stages.6.label>매우 인상적인 욕실</UsedPrivateBathroom.stages.6.label>
  <UsedPrivateBathroom.stages.6.description>내 욕실은 매우 인상적이야</UsedPrivateBathroom.stages.6.description>
  <UsedPrivateBathroom.stages.7.label>익스트림 인상적인 욕실</UsedPrivateBathroom.stages.7.label>
  <UsedPrivateBathroom.stages.7.description>내 욕실은 정말 인상적이야</UsedPrivateBathroom.stages.7.description>
  <UsedPrivateBathroom.stages.8.label>믿을 수 없을만큼 인상적인 욕실</UsedPrivateBathroom.stages.8.label>
  <UsedPrivateBathroom.stages.8.description>내 욕실은 믿을 수 없을 정도로 인상적!</UsedPrivateBathroom.stages.8.description>
  <UsedPrivateBathroom.stages.9.label>경이로운 인상적인 욕실</UsedPrivateBathroom.stages.9.label>
  <UsedPrivateBathroom.stages.9.description>내 욕실은 상상할 수있는 최고의 장소야. 훌륭해!</UsedPrivateBathroom.stages.9.description>


</LanguageData>